cidipi/__init__.py
cidipi/client.py
cidipi/interface.py
cidipi/models.py
cidipi/protocols/__init__.py
cidipi/protocols/commands.py
cidipi/protocols/events.py
cidipi/protocols/types.py
cidipi/py.typed
cidipi/utils.py
cidipi-0.2.0.dist-info/LICENSE
cidipi-0.2.0.dist-info/METADATA
cidipi-0.2.0.dist-info/WHEEL
cidipi-0.2.0.dist-info/RECORD
